pycounts_sl/__init__.py
pycounts_sl/plotting.py
pycounts_sl/pycounts_sl.py
pycounts_sl-0.1.0.dist-info/LICENSE
pycounts_sl-0.1.0.dist-info/WHEEL
pycounts_sl-0.1.0.dist-info/METADATA
pycounts_sl-0.1.0.dist-info/RECORD
