Metadata-Version: 2.1
Name: pycounts-sl
Version: 0.1.0
Summary: This is a test Python package to learn python package creation process. This package includes simple functions operates on text file in Python.
License: MIT
Author: Steven Lio
Requires-Python: >=3.9,<4.0
Classifier: License :: OSI Approved :: MIT License
Classifier: Programming Language :: Python :: 3
Classifier: Programming Language :: Python :: 3.10
Classifier: Programming Language :: Python :: 3.9
Requires-Dist: matplotlib (>=3.5.1,<4.0.0)
